prompt_hot_reloading/__init__.py
prompt_hot_reloading/prompt_registry/__init__.py
prompt_hot_reloading/prompt_registry/create_prompt_registry.py
prompt_hot_reloading/prompt_registry/prompt_map.py
prompt_hot_reloading/prompt_registry/prompt_registry.py
prompt_hot_reloading/prompt_source/__init__.py
prompt_hot_reloading/prompt_source/file_system_source.py
prompt_hot_reloading/prompt_source/prompt_source.py
prompt_hot_reloading/prompt_source/s3_polling_source.py
prompt_hot_reloading-0.1.4.dist-info/licenses/LICENSE
prompt_hot_reloading-0.1.4.dist-info/METADATA
prompt_hot_reloading-0.1.4.dist-info/WHEEL
prompt_hot_reloading-0.1.4.dist-info/top_level.txt
prompt_hot_reloading-0.1.4.dist-info/RECORD
