Metadata-Version: 2.4
Name: prompt-hot-reloading
Version: 0.1.4
Summary: Hot-reloadable prompt library for Python apps
Author: Steve Krawczyk
Author-email: Steve Krawczyk <steve@krawfy.com>
License: MIT
Classifier: Programming Language :: Python :: 3
Classifier: License :: OSI Approved :: MIT License
Classifier: Operating System :: OS Independent
License-File: LICENSE
Requires-Dist: watchdog
Requires-Dist: readerwriterlock
Requires-Dist: boto3; extra == "s3"
Dynamic: license-file
